toggl_reporter/__init__.py
toggl_reporter/__main__.py
toggl_reporter/cli.py
toggl_reporter/dates.py
toggl_reporter/logic.py
toggl_reporter/toggl_api.py
toggl_reporter-0.0.3.data/data/requirements/requirements.txt
toggl_reporter-0.0.3.dist-info/LICENSE
toggl_reporter-0.0.3.dist-info/METADATA
toggl_reporter-0.0.3.dist-info/WHEEL
toggl_reporter-0.0.3.dist-info/entry_points.txt
toggl_reporter-0.0.3.dist-info/top_level.txt
toggl_reporter-0.0.3.dist-info/RECORD
