Metadata-Version: 2.1
Name: toggl-reporter
Version: 0.0.3
Summary: A tool to build daily reports from Toggle with nice grouping
Home-page: UNKNOWN
Author: Ilya Siganov
Author-email: ilya.blan4@gmail.com
License: MIT
Project-URL: source, https://github.com/senior-sigan/toggl-reporter
Platform: UNKNOWN
Classifier: License :: OSI Approved :: MIT License
Classifier: Programming Language :: Python
Classifier: Programming Language :: Python :: 3.6
Classifier: Programming Language :: Python :: 3.7
Classifier: Programming Language :: Python :: 3.8
Classifier: Environment :: Console
Classifier: Topic :: Utilities
Requires-Python: >=3.6
Requires-Dist: requests
